CHANGELOG.md
LICENSE
MANIFEST.in
NOTICE
README.md
setup.cfg
setup.py
encrypticoin_ssi/__init__.py
encrypticoin_ssi/balance.py
encrypticoin_ssi/balance_change.py
encrypticoin_ssi/client.py
encrypticoin_ssi/error.py
encrypticoin_ssi/message.py
encrypticoin_ssi.egg-info/PKG-INFO
encrypticoin_ssi.egg-info/SOURCES.txt
encrypticoin_ssi.egg-info/dependency_links.txt
encrypticoin_ssi.egg-info/requires.txt
encrypticoin_ssi.egg-info/top_level.txt
requirements/base.in
requirements/test.in