Metadata-Version: 2.1
Name: encrypticoin-ssi
Version: 1.1.0
Summary: Service-Server-Integration library for Etalon Token Integration API
Home-page: https://github.com/encrypticoin-uab/encrypticoin-ssi-python
Author: Nándor Mátravölgyi
Author-email: dev@etalon.cash
License: Apache 2.0
Classifier: Programming Language :: Python :: 3
Classifier: Programming Language :: Python :: 3.8
Classifier: Programming Language :: Python :: 3.9
Classifier: Programming Language :: Python :: 3.10
Classifier: Programming Language :: Python :: Implementation :: CPython
Classifier: Intended Audience :: Developers
Classifier: License :: OSI Approved :: Apache Software License
Requires-Python: >=3.8
Provides-Extra: test
License-File: LICENSE
License-File: NOTICE
